CPrimerDi4BanKehouXitiJiedaDi118ZhangWanzhengban/README.md
CPrimerDi4BanKehouXitiJiedaDi118ZhangWanzhengban/__init__.py
CPrimerDi4BanKehouXitiJiedaDi118ZhangWanzhengban/__main__.py
CPrimerDi4BanKehouXitiJiedaDi118ZhangWanzhengban/file.pdf
CPrimerDi4BanKehouXitiJiedaDi118ZhangWanzhengban/index.html
c_primer_di_4_ban_kehou_xiti_jieda_di_1_18_zhang_wanzhengban-2024.3.2.0.dist-info/METADATA
c_primer_di_4_ban_kehou_xiti_jieda_di_1_18_zhang_wanzhengban-2024.3.2.0.dist-info/WHEEL
c_primer_di_4_ban_kehou_xiti_jieda_di_1_18_zhang_wanzhengban-2024.3.2.0.dist-info/entry_points.txt
c_primer_di_4_ban_kehou_xiti_jieda_di_1_18_zhang_wanzhengban-2024.3.2.0.dist-info/top_level.txt
c_primer_di_4_ban_kehou_xiti_jieda_di_1_18_zhang_wanzhengban-2024.3.2.0.dist-info/RECORD
